xdwarf/__init__.py
xdwarf/dwarf.py
xdwarf-0.1.0.dist-info/LICENSE
xdwarf-0.1.0.dist-info/METADATA
xdwarf-0.1.0.dist-info/WHEEL
xdwarf-0.1.0.dist-info/top_level.txt
xdwarf-0.1.0.dist-info/RECORD
