Metadata-Version: 2.1
Name: xdwarf
Version: 0.1.0
Summary: UNKNOWN
Home-page: https://github.com/raynardj/xdwarf
License: GPLv3+
Project-URL: Documentation, https://github.com/raynardj/xdwarf
Project-URL: Tracker, https://github.com/raynardj/xdwarf/issues
Platform: UNKNOWN
Classifier: Development Status :: 3 - Alpha
Classifier: Intended Audience :: End Users/Desktop
Classifier: License :: OSI Approved :: GNU General Public License v3 (GPLv3)
Classifier: Natural Language :: English
Classifier: Programming Language :: Python :: 3.6
Classifier: Programming Language :: Python :: 3.7
Classifier: Programming Language :: Python :: 3.8
Classifier: Programming Language :: Python :: 3.9
Classifier: Programming Language :: Python :: 3.10
Requires-Python: >=3.6
Requires-Dist: rust-dwarf
Requires-Dist: pandas
